pullkin/__init__.py
pullkin/__main__.py
pullkin/aioclient.py
pullkin/client_base.py
pullkin/models/__init__.py
pullkin/models/credentials.py
pullkin/models/message.py
pullkin/models/service/__init__.py
pullkin/models/service/responses.py
pullkin/proto/__init__.py
pullkin/proto/android_checkin_proto.py
pullkin/proto/checkin_proto.py
pullkin/proto/mcs_proto.py
tests/__init__.py
tests/conftest.py
tests/test_login.py
tests/test_receiving.py
tests/test_registration.py
tests/testdata.py
pullkin-0.14.0.dist-info/LICENSE
pullkin-0.14.0.dist-info/METADATA
pullkin-0.14.0.dist-info/WHEEL
pullkin-0.14.0.dist-info/top_level.txt
pullkin-0.14.0.dist-info/RECORD
