Metadata-Version: 2.1
Name: pullkin
Version: 0.14.0
Summary: Subscribe to GCM/FCM and receive notifications like an android app
Home-page: https://github.com/WhiteApfel/pullkin
Author: WhiteApfel
Author-email: white@pfel.ru
License: Mozilla Public License 2.0
Keywords: fcm gcm push notification receive firebase google
Classifier: Programming Language :: Python :: 3
Classifier: Programming Language :: Python :: 3.8
Classifier: Programming Language :: Python :: 3.9
Classifier: Programming Language :: Python :: 3.10
Classifier: Programming Language :: Python :: 3.11
Classifier: Programming Language :: Python :: Implementation :: PyPy
Classifier: Intended Audience :: Developers
Classifier: Topic :: Software Development :: Libraries
License-File: LICENSE
Requires-Dist: betterproto ~=1.2.5
Requires-Dist: cryptography ~=42.0.5
Requires-Dist: http-ece ~=1.2.0
Requires-Dist: httpx ~=0.27.0
Requires-Dist: loguru ~=0.7.2
Requires-Dist: oscrypto ~=1.3.0
Requires-Dist: pydantic ~=2.6.2
Requires-Dist: python-dotenv ~=1.0.1
Requires-Dist: ujson ~=5.9.0
